alkali/__init__.py
alkali/database.py
alkali/fields.py
alkali/manager.py
alkali/memoized_property.py
alkali/metamodel.py
alkali/model.py
alkali/peekorator.py
alkali/query.py
alkali/reify.py
alkali/relmanager.py
alkali/signals.py
alkali/utils.py
alkali/storage/__init__.py
alkali/storage/csv.py
alkali/storage/file.py
alkali/storage/json.py
alkali/storage/multi.py
alkali/storage/storage.py
alkali-0.7.3.dist-info/LICENSE.md
alkali-0.7.3.dist-info/METADATA
alkali-0.7.3.dist-info/WHEEL
alkali-0.7.3.dist-info/top_level.txt
alkali-0.7.3.dist-info/RECORD
